SMBH/__init__.py
DR16_MassFunction-1.0.0.dist-info/LICENSE
DR16_MassFunction-1.0.0.dist-info/METADATA
DR16_MassFunction-1.0.0.dist-info/WHEEL
DR16_MassFunction-1.0.0.dist-info/top_level.txt
DR16_MassFunction-1.0.0.dist-info/RECORD
