Metadata-Version: 2.1
Name: DR16-MassFunction
Version: 1.0.0
Summary: calculating the mass-luminosity functions of quasars on any complete catalog
License: LICENSE
License-File: LICENSE
